transformer_korean/__init__.py
transformer_korean/attention.py
transformer_korean/custom_scheduler.py
transformer_korean/decoder.py
transformer_korean/decoder_layer.py
transformer_korean/encoder.py
transformer_korean/encoder_layer.py
transformer_korean/masker.py
transformer_korean/positional_encoder.py
transformer_korean/preprocess.py
transformer_korean/run_training.py
transformer_korean/transformer.py
transformer_korean-0.0.3.dist-info/METADATA
transformer_korean-0.0.3.dist-info/WHEEL
transformer_korean-0.0.3.dist-info/top_level.txt
transformer_korean-0.0.3.dist-info/RECORD
