Metadata-Version: 2.1
Name: transformer-korean
Version: 0.0.3
Summary: Text-to-Text Transformer for Korean QA Task
Home-page: https://github.com/yeontaek/Text-to-Text-Transformer
Author: yeontaek oh
Author-email: oh31400@naver.com
License: MIT
Platform: UNKNOWN
Classifier: Programming Language :: Python :: 3.5
Classifier: Programming Language :: Python :: 3.6
Classifier: Programming Language :: Python :: 3.7
Requires-Python: >=3.5
Requires-Dist: tensorflow (>=2.0)
Requires-Dist: tensorflow-datasets (>=1.3.2)
Requires-Dist: pandas (>=0.24.2)
Requires-Dist: numpy (>=1.16.3)
Requires-Dist: six (>=1.12.0)
